{
  "content": "\nOberon Loops and Conditions\n===========================\n\nBy R. S. Doiel, 2020-04-19\n\nThis is the four post in the [Mostly Oberon](../11/Mostly-Oberon.html) series. Mostly Oberon documents my exploration of the Oberon Language, Oberon System and the various rabbit holes I will inevitably fall into.\n\n## Data Flow\n\nOberon is a small systems language and while it is minimalist.\nIt provides you with the necessary primitives to get things done.\nI've touched on code organization, basic types and basic type\nextensions in the previous articles.  I have shown the basic\ncontrol statements but have not talked about them yet.\n\nOberon offers four basic control statements. \n\nIF, ELSIF, ELSE\n: Basic condition test and execution\n\nASSERT\n: A mechanism to trigger a program halt\n\nWHILE DO, ELSIF DO\n: The Loop structure in the language (aside from recursive procedures)\n\nFOR TO, FOR TO BY\n: A counting Loop where incrementing a counter by an integer value (e.g. 1 or by a specified constant).\n\n## IF, ELSIF, ELSE\n\nThe first two provide for conditional statements of the form\nif a condition is true do something. Almost ever computer language\nhas some form of a conditional express and the Oberon IF, ELSIF,\nELSE typical of what you find is more computer languages today.\nBoth ELSIF and ELSE are optional.\n\n```Oberon\n    IF (s = \"Freda\") OR (s = \"Mojo\") THEN\n      Out.String(\"Wowie Zowie! I remember you from ZBS stories.\");Out.Ln;\n    ELSIF (s = \"Bilbo\") OR (s = \"Gandolf\") THEN\n      Out.String(\"Greets, I remember from the Hobbit.\");Out.Ln;\n    ELSE\n      Out.String(\"Glad to meet you \");Out.String(s);Out.Ln;\n    END;\n```\n\n## ASSERT\n\nThe second expression, ASSERT, is a little different. If ASSERT\nevaluates an expression that is FALSE then your program is halted.\nThis is like combining an \"if EXPR is false then system exit\".\n\n```Oberon\n    Out.String(\"Should I continue? Y/n \");\n    In.Line(s);\n    Out.Ln;\n    ASSERT((s = \"Y\") OR (s = \"y\"));\n    (* If you didn't enter Y or y the program will halt *)\n```\n\n\n## WHILE DO, ELSIF DO\n\nOberon-07 also provides two loop structures. These are very \nsimilar to other languages as well. The only expectation is that\na while loop may contain an ELSIF which continues the loop\nexecution until both clauses return FALSE.\n\nThe basic while loop, counting 1 to 10.\n\n```Oberon\n    i := 0;\n    WHILE i < 10 DO\n       i := i + 1;\n       Out.Int(i, 1);Out.String(\" \");\n    END;\n```\n\nA while, elsif loop, counting 1 to 10, then 10 to 100 by 10.\n\n```Oberon\n    i := 0;\n    WHILE i < 10 DO\n       i := i + 1;\n       Out.Int(i, 1); Out.String(\" \");\n    ELSIF i < 100 DO\n       i := i + 10;\n       Out.Int(i, 1);Out.String(\" \");\n    END;\n```\n\n\n## FOR Loops\n\nThe FOR loop in Oberon is very similar to modern FOR loops.\nThe FOR loop increments an integer value with in a range.\nYou the default increments the start value by 1 but if a \nBY clause is included you can control how the increment value\nworks.\n\nRegular for loop, `i` is incremented by 1.\n\n```Oberon\n    FOR i := 1 TO 10 DO\n       Out.Int(i, 1);Out.String(\" \");\n    END;\n```\n\nUsing a BY clause incrementing `i` by 2.\n\n```Oberon\n    FOR i := 0 TO 20 BY 2  DO\n       Out.Int(i, 1);Out.String(\" \");\n    END;\n```\n\n\n## Putting it all together\n\nThe following [module](LoopsAndConditions.Mod) demonstrates\nthe conditional and loop syntax.\n\n```Oberon\n    MODULE LoopsAndConditions;\n      IMPORT In, Out;\n    \n    PROCEDURE IfElsifElseDemo;\n      VAR s : ARRAY 128 OF CHAR;\n    BEGIN\n      Out.String(\"Enter your name: \");\n      In.Line(s);\n      Out.Ln;\n      IF (s = \"Freda\") OR (s = \"Mojo\") THEN\n        Out.String(\"Wowie Zowie! I remember you from ZBS stories.\");Out.Ln;\n      ELSIF (s = \"Bilbo\") OR (s = \"Gandolf\") THEN\n        Out.String(\"Greets, I remember from the Hobbit.\");Out.Ln;\n      ELSE\n        Out.String(\"Glad to meet you \");Out.String(s);Out.Ln;\n      END;\n    END IfElsifElseDemo;\n    \n    PROCEDURE AssertDemo;\n      VAR s : ARRAY 128 OF CHAR;\n    BEGIN\n      Out.String(\"Should I continue? Y/n \");\n      In.Line(s);\n      Out.Ln;\n      ASSERT((s = \"Y\") OR (s = \"y\"));\n    END AssertDemo;\n    \n    PROCEDURE WhileDemo;\n      VAR i : INTEGER;\n    BEGIN\n      Out.String(\"Basic WHILE counting from 1 to 10\");Out.Ln;\n      i := 0;\n      WHILE i < 10 DO\n         i := i + 1;\n         Out.Int(i, 1);Out.String(\" \");\n      END;\n      Out.Ln;\n      Out.String(\"WHILE ELSIF, count 1 to 10 THEN 10 to 100\");Out.Ln;\n      i := 0;\n      WHILE i < 10 DO\n         i := i + 1;\n         Out.Int(i, 1); Out.String(\" \");\n      ELSIF i < 100 DO\n         i := i + 10;\n         Out.Int(i, 1);Out.String(\" \");\n      END;\n      Out.Ln;\n      Out.String(\"Demo of while loop counting one to ten, then by tenths.\");\n    END WhileDemo;\n    \n    PROCEDURE ForDemo;\n      VAR i : INTEGER;\n    BEGIN\n      Out.String(\"Basic FOR LOOP counting from 1 to 10\");Out.Ln;\n      FOR i := 1 TO 10 DO\n         Out.Int(i, 1);Out.String(\" \");\n      END;\n      Out.Ln;\n      Out.String(\"FOR loop counting by twos 1 to 20\");Out.Ln;\n      FOR i := 0 TO 20 BY 2  DO\n         Out.Int(i, 1);Out.String(\" \");\n      END;\n      Out.Ln;\n    END ForDemo;\n    \n    BEGIN\n      IfElsifElseDemo;\n      AssertDemo;\n      WhileDemo;\n      ForDemo;\n    END LoopsAndConditions.\n```\n\n\n### Next and Previous\n\n+ Next [Combining Oberon-07 and C with OBNC](../../05/01/Combining-Oberon-and-C.html)\n+ Previous [Basic Types](../18/Mostly-Oberon-Basic-Types.html)\n\n",
  "content_ast": {
    "children": [
      {
        "children": [
          {
            "type": "text",
            "value": "Oberon Loops and Conditions"
          }
        ],
        "depth": 1,
        "type": "heading"
      },
      {
        "children": [
          {
            "type": "text",
            "value": "By R. S. Doiel, 2020-04-19"
          }
        ],
        "type": "paragraph"
      },
      {
        "children": [
          {
            "type": "text",
            "value": "This is the four post in the "
          },
          {
            "children": [
              {
                "type": "text",
                "value": "Mostly Oberon"
              }
            ],
            "type": "link",
            "url": "../11/Mostly-Oberon.html"
          },
          {
            "type": "text",
            "value": " series. Mostly Oberon documents my exploration of the Oberon Language, Oberon System and the various rabbit holes I will inevitably fall into."
          }
        ],
        "type": "paragraph"
      },
      {
        "children": [
          {
            "type": "text",
            "value": "Data Flow"
          }
        ],
        "depth": 2,
        "type": "heading"
      },
      {
        "children": [
          {
            "type": "text",
            "value": "Oberon is a small systems language and while it is minimalist.\nIt provides you with the necessary primitives to get things done.\nI've touched on code organization, basic types and basic type\nextensions in the previous articles.  I have shown the basic\ncontrol statements but have not talked about them yet."
          }
        ],
        "type": "paragraph"
      },
      {
        "children": [
          {
            "type": "text",
            "value": "Oberon offers four basic control statements."
          }
        ],
        "type": "paragraph"
      },
      {
        "children": [
          {
            "type": "text",
            "value": "IF, ELSIF, ELSE\n: Basic condition test and execution"
          }
        ],
        "type": "paragraph"
      },
      {
        "children": [
          {
            "type": "text",
            "value": "ASSERT\n: A mechanism to trigger a program halt"
          }
        ],
        "type": "paragraph"
      },
      {
        "children": [
          {
            "type": "text",
            "value": "WHILE DO, ELSIF DO\n: The Loop structure in the language (aside from recursive procedures)"
          }
        ],
        "type": "paragraph"
      },
      {
        "children": [
          {
            "type": "text",
            "value": "FOR TO, FOR TO BY\n: A counting Loop where incrementing a counter by an integer value (e.g. 1 or by a specified constant)."
          }
        ],
        "type": "paragraph"
      },
      {
        "children": [
          {
            "type": "text",
            "value": "IF, ELSIF, ELSE"
          }
        ],
        "depth": 2,
        "type": "heading"
      },
      {
        "children": [
          {
            "type": "text",
            "value": "The first two provide for conditional statements of the form\nif a condition is true do something. Almost ever computer language\nhas some form of a conditional express and the Oberon IF, ELSIF,\nELSE typical of what you find is more computer languages today.\nBoth ELSIF and ELSE are optional."
          }
        ],
        "type": "paragraph"
      },
      {
        "lang": "Oberon",
        "type": "code",
        "value": "    IF (s = \"Freda\") OR (s = \"Mojo\") THEN\n      Out.String(\"Wowie Zowie! I remember you from ZBS stories.\");Out.Ln;\n    ELSIF (s = \"Bilbo\") OR (s = \"Gandolf\") THEN\n      Out.String(\"Greets, I remember from the Hobbit.\");Out.Ln;\n    ELSE\n      Out.String(\"Glad to meet you \");Out.String(s);Out.Ln;\n    END;"
      },
      {
        "children": [
          {
            "type": "text",
            "value": "ASSERT"
          }
        ],
        "depth": 2,
        "type": "heading"
      },
      {
        "children": [
          {
            "type": "text",
            "value": "The second expression, ASSERT, is a little different. If ASSERT\nevaluates an expression that is FALSE then your program is halted.\nThis is like combining an \"if EXPR is false then system exit\"."
          }
        ],
        "type": "paragraph"
      },
      {
        "lang": "Oberon",
        "type": "code",
        "value": "    Out.String(\"Should I continue? Y/n \");\n    In.Line(s);\n    Out.Ln;\n    ASSERT((s = \"Y\") OR (s = \"y\"));\n    (* If you didn't enter Y or y the program will halt *)"
      },
      {
        "children": [
          {
            "type": "text",
            "value": "WHILE DO, ELSIF DO"
          }
        ],
        "depth": 2,
        "type": "heading"
      },
      {
        "children": [
          {
            "type": "text",
            "value": "Oberon-07 also provides two loop structures. These are very\nsimilar to other languages as well. The only expectation is that\na while loop may contain an ELSIF which continues the loop\nexecution until both clauses return FALSE."
          }
        ],
        "type": "paragraph"
      },
      {
        "children": [
          {
            "type": "text",
            "value": "The basic while loop, counting 1 to 10."
          }
        ],
        "type": "paragraph"
      },
      {
        "lang": "Oberon",
        "type": "code",
        "value": "    i := 0;\n    WHILE i < 10 DO\n       i := i + 1;\n       Out.Int(i, 1);Out.String(\" \");\n    END;"
      },
      {
        "children": [
          {
            "type": "text",
            "value": "A while, elsif loop, counting 1 to 10, then 10 to 100 by 10."
          }
        ],
        "type": "paragraph"
      },
      {
        "lang": "Oberon",
        "type": "code",
        "value": "    i := 0;\n    WHILE i < 10 DO\n       i := i + 1;\n       Out.Int(i, 1); Out.String(\" \");\n    ELSIF i < 100 DO\n       i := i + 10;\n       Out.Int(i, 1);Out.String(\" \");\n    END;"
      },
      {
        "children": [
          {
            "type": "text",
            "value": "FOR Loops"
          }
        ],
        "depth": 2,
        "type": "heading"
      },
      {
        "children": [
          {
            "type": "text",
            "value": "The FOR loop in Oberon is very similar to modern FOR loops.\nThe FOR loop increments an integer value with in a range.\nYou the default increments the start value by 1 but if a\nBY clause is included you can control how the increment value\nworks."
          }
        ],
        "type": "paragraph"
      },
      {
        "children": [
          {
            "type": "text",
            "value": "Regular for loop, "
          },
          {
            "type": "inlineCode",
            "value": "i"
          },
          {
            "type": "text",
            "value": " is incremented by 1."
          }
        ],
        "type": "paragraph"
      },
      {
        "lang": "Oberon",
        "type": "code",
        "value": "    FOR i := 1 TO 10 DO\n       Out.Int(i, 1);Out.String(\" \");\n    END;"
      },
      {
        "children": [
          {
            "type": "text",
            "value": "Using a BY clause incrementing "
          },
          {
            "type": "inlineCode",
            "value": "i"
          },
          {
            "type": "text",
            "value": " by 2."
          }
        ],
        "type": "paragraph"
      },
      {
        "lang": "Oberon",
        "type": "code",
        "value": "    FOR i := 0 TO 20 BY 2  DO\n       Out.Int(i, 1);Out.String(\" \");\n    END;"
      },
      {
        "children": [
          {
            "type": "text",
            "value": "Putting it all together"
          }
        ],
        "depth": 2,
        "type": "heading"
      },
      {
        "children": [
          {
            "type": "text",
            "value": "The following "
          },
          {
            "children": [
              {
                "type": "text",
                "value": "module"
              }
            ],
            "type": "link",
            "url": "LoopsAndConditions.Mod"
          },
          {
            "type": "text",
            "value": " demonstrates\nthe conditional and loop syntax."
          }
        ],
        "type": "paragraph"
      },
      {
        "lang": "Oberon",
        "type": "code",
        "value": "    MODULE LoopsAndConditions;\n      IMPORT In, Out;\n    \n    PROCEDURE IfElsifElseDemo;\n      VAR s : ARRAY 128 OF CHAR;\n    BEGIN\n      Out.String(\"Enter your name: \");\n      In.Line(s);\n      Out.Ln;\n      IF (s = \"Freda\") OR (s = \"Mojo\") THEN\n        Out.String(\"Wowie Zowie! I remember you from ZBS stories.\");Out.Ln;\n      ELSIF (s = \"Bilbo\") OR (s = \"Gandolf\") THEN\n        Out.String(\"Greets, I remember from the Hobbit.\");Out.Ln;\n      ELSE\n        Out.String(\"Glad to meet you \");Out.String(s);Out.Ln;\n      END;\n    END IfElsifElseDemo;\n    \n    PROCEDURE AssertDemo;\n      VAR s : ARRAY 128 OF CHAR;\n    BEGIN\n      Out.String(\"Should I continue? Y/n \");\n      In.Line(s);\n      Out.Ln;\n      ASSERT((s = \"Y\") OR (s = \"y\"));\n    END AssertDemo;\n    \n    PROCEDURE WhileDemo;\n      VAR i : INTEGER;\n    BEGIN\n      Out.String(\"Basic WHILE counting from 1 to 10\");Out.Ln;\n      i := 0;\n      WHILE i < 10 DO\n         i := i + 1;\n         Out.Int(i, 1);Out.String(\" \");\n      END;\n      Out.Ln;\n      Out.String(\"WHILE ELSIF, count 1 to 10 THEN 10 to 100\");Out.Ln;\n      i := 0;\n      WHILE i < 10 DO\n         i := i + 1;\n         Out.Int(i, 1); Out.String(\" \");\n      ELSIF i < 100 DO\n         i := i + 10;\n         Out.Int(i, 1);Out.String(\" \");\n      END;\n      Out.Ln;\n      Out.String(\"Demo of while loop counting one to ten, then by tenths.\");\n    END WhileDemo;\n    \n    PROCEDURE ForDemo;\n      VAR i : INTEGER;\n    BEGIN\n      Out.String(\"Basic FOR LOOP counting from 1 to 10\");Out.Ln;\n      FOR i := 1 TO 10 DO\n         Out.Int(i, 1);Out.String(\" \");\n      END;\n      Out.Ln;\n      Out.String(\"FOR loop counting by twos 1 to 20\");Out.Ln;\n      FOR i := 0 TO 20 BY 2  DO\n         Out.Int(i, 1);Out.String(\" \");\n      END;\n      Out.Ln;\n    END ForDemo;\n    \n    BEGIN\n      IfElsifElseDemo;\n      AssertDemo;\n      WhileDemo;\n      ForDemo;\n    END LoopsAndConditions."
      },
      {
        "children": [
          {
            "type": "text",
            "value": "Next and Previous"
          }
        ],
        "depth": 3,
        "type": "heading"
      },
      {
        "children": [
          {
            "children": [
              {
                "children": [
                  {
                    "type": "text",
                    "value": "Next "
                  },
                  {
                    "children": [
                      {
                        "type": "text",
                        "value": "Combining Oberon-07 and C with OBNC"
                      }
                    ],
                    "type": "link",
                    "url": "../../05/01/Combining-Oberon-and-C.html"
                  }
                ],
                "type": "paragraph"
              }
            ],
            "spread": false,
            "type": "listItem"
          },
          {
            "children": [
              {
                "children": [
                  {
                    "type": "text",
                    "value": "Previous "
                  },
                  {
                    "children": [
                      {
                        "type": "text",
                        "value": "Basic Types"
                      }
                    ],
                    "type": "link",
                    "url": "../18/Mostly-Oberon-Basic-Types.html"
                  }
                ],
                "type": "paragraph"
              }
            ],
            "spread": false,
            "type": "listItem"
          }
        ],
        "ordered": false,
        "spread": false,
        "type": "list"
      }
    ],
    "type": "root"
  },
  "data": {
    "author": "rsdoiel@gmail.com (R. S. Doiel)",
    "copyright": "copyright (c) 2020, R. S. Doiel",
    "date": "2020-04-19",
    "keywords": [
      "Oberon",
      "programming"
    ],
    "license": "https://creativecommons.org/licenses/by-sa/4.0/",
    "number": 4,
    "series": "Mostly Oberon",
    "title": "Oberon Loops and Conditions"
  }
}